qualys_etl/README.md
qualys_etl/__init__.py
qualys_etl/qetl_manage_user.py
qualys_etl/etld_asset_inventory/__init__.py
qualys_etl/etld_asset_inventory/asset_inventory_01_spawn_workflow_manager.py
qualys_etl/etld_asset_inventory/asset_inventory_02_workflow_manager.py
qualys_etl/etld_asset_inventory/asset_inventory_03_extract_controller.py
qualys_etl/etld_asset_inventory/asset_inventory_04_extract_from_qualys.py
qualys_etl/etld_asset_inventory/asset_inventory_05_transform_load_json_to_sqlite.py
qualys_etl/etld_asset_inventory/asset_inventory_06_distribution.py
qualys_etl/etld_cs_images/__init__.py
qualys_etl/etld_cs_images/pcrs_01_spawn_workflow_manager.py
qualys_etl/etld_cs_images/pcrs_02_workflow_manager.py
qualys_etl/etld_cs_images/pcrs_03_extract_controller.py
qualys_etl/etld_cs_images/pcrs_04_extract_from_qualys.py
qualys_etl/etld_cs_images/pcrs_05_transform_load_json_to_sqlite.py
qualys_etl/etld_cs_images/pcrs_05_transform_load_json_to_sqlite_orig.py
qualys_etl/etld_cs_images/pcrs_06_distribution.py
qualys_etl/etld_data_flow/__init__.py
qualys_etl/etld_data_flow/df_01_spawn_workflow_manager.py
qualys_etl/etld_data_flow/df_02_workflow_manager.py
qualys_etl/etld_data_flow/df_03_extract_controller.py
qualys_etl/etld_data_flow/df_04_extract_from_qualys.py
qualys_etl/etld_data_flow/df_05_transform_load_json_to_sqlite.py
qualys_etl/etld_data_flow/df_05_transform_load_json_to_sqlite_orig.py
qualys_etl/etld_data_flow/df_06_distribution.py
qualys_etl/etld_host_list/__init__.py
qualys_etl/etld_host_list/host_list_01_spawn_workflow_manager.py
qualys_etl/etld_host_list/host_list_02_workflow_manager.py
qualys_etl/etld_host_list/host_list_03_extract_controller.py
qualys_etl/etld_host_list/host_list_04_extract_from_qualys.py
qualys_etl/etld_host_list/host_list_05_transform_load_xml_to_sqlite.py
qualys_etl/etld_host_list/host_list_06_distribution.py
qualys_etl/etld_host_list_detection/__init__.py
qualysetl-0.9.9.dist-info/licenses/LICENSE.txt
qualysetl-0.9.9.dist-info/METADATA
qualysetl-0.9.9.dist-info/WHEEL
qualysetl-0.9.9.dist-info/top_level.txt
qualysetl-0.9.9.dist-info/RECORD
