Metadata-Version: 2.4
Name: qualysetl
Version: 0.9.9
Summary: Qualys API Best Practices Series - ETL Blueprint Example Code within Python Virtual Environment
Home-page: https://pypi.org/project/qualysetl/
Author: David Gregory
Author-email: dgregory@qualys.com, dave@davidgregory.com
License: Apache
Project-URL: Documentation, https://dg-cafe.github.io/qualysetl/
Project-URL: Qualys Video Series, https://blog.qualys.com/tag/api-best-practices-series
Keywords: qualys,etl,qualys.com,david gregory,qualysetl,qualysapi
Classifier: Development Status :: 4 - Beta
Classifier: Intended Audience :: Developers
Classifier: License :: OSI Approved :: Apache Software License
Classifier: Programming Language :: Python :: 3.8
Classifier: Programming Language :: Python :: 3.9
Classifier: Programming Language :: Python :: 3.10
Classifier: Programming Language :: Python :: 3.11
Classifier: Programming Language :: Python :: 3 :: Only
Classifier: Operating System :: POSIX :: Linux
Requires-Python: >=3.8.5
License-File: LICENSE.txt
Dynamic: author
Dynamic: author-email
Dynamic: classifier
Dynamic: description
Dynamic: description-content-type
Dynamic: home-page
Dynamic: keywords
Dynamic: license
Dynamic: license-file
Dynamic: project-url
Dynamic: requires-python
Dynamic: summary
